{
  "parameters": {
    "api-version": "2022-06-17-preview",
    "subscriptionId": "kridwgignlpsmjcnbmefqjf",
    "resourceGroupName": "rgopenapi",
    "encryptedTransportName": "SGAEEIb",
    "resource": {
      "properties": {
        "displayName": "iwjduwybhvvyzgxxcspxvkblcqnfhh",
        "regionDisplayName": "aqlcyrpnvshurualudsmh",
        "regionType": "chnfpecvngwgzepokthkblhjg",
        "regionCategory": "wzzkpcu",
        "geographyGroup": "yxygit",
        "provisioningState": "Succeeded"
      },
      "tags": {
        "key3728": "wnvlvgnwffdaxqwtgbjfx"
      },
      "location": "glxsvyqlxllnwookckibkllfokboz"
    }
  },
  "responses": {
    "200": {
      "body": {
        "properties": {
          "displayName": "iwjduwybhvvyzgxxcspxvkblcqnfhh",
          "regionDisplayName": "aqlcyrpnvshurualudsmh",
          "regionType": "chnfpecvngwgzepokthkblhjg",
          "regionCategory": "wzzkpcu",
          "geographyGroup": "yxygit",
          "provisioningState": "Succeeded"
        },
        "tags": {
          "key3728": "wnvlvgnwffdaxqwtgbjfx"
        },
        "location": "glxsvyqlxllnwookckibkllfokboz",
        "id": "qw",
        "name": "xutlwwnvwttaiugkiwuktkj",
        "type": "sifuqapvehcaaurgj",
        "systemData": {
          "createdBy": "aoscyngoqe",
          "createdByType": "User",
          "createdAt": "2022-10-11T16:05:56.509Z",
          "lastModifiedBy": "gvrefosylrhfvnqkqjx",
          "lastModifiedByType": "User",
          "lastModifiedAt": "2022-10-11T16:05:56.509Z"
        }
      }
    },
    "201": {
      "headers": {
        "Azure-AsyncOperation": "https://contoso.com/operationstatus"
      },
      "body": {
        "properties": {
          "displayName": "iwjduwybhvvyzgxxcspxvkblcqnfhh",
          "regionDisplayName": "aqlcyrpnvshurualudsmh",
          "regionType": "chnfpecvngwgzepokthkblhjg",
          "regionCategory": "wzzkpcu",
          "geographyGroup": "yxygit",
          "provisioningState": "Succeeded"
        },
        "tags": {
          "key3728": "wnvlvgnwffdaxqwtgbjfx"
        },
        "location": "glxsvyqlxllnwookckibkllfokboz",
        "id": "qw",
        "name": "xutlwwnvwttaiugkiwuktkj",
        "type": "sifuqapvehcaaurgj",
        "systemData": {
          "createdBy": "aoscyngoqe",
          "createdByType": "User",
          "createdAt": "2022-10-11T16:05:56.509Z",
          "lastModifiedBy": "gvrefosylrhfvnqkqjx",
          "lastModifiedByType": "User",
          "lastModifiedAt": "2022-10-11T16:05:56.509Z"
        }
      }
    }
  }
}