{
  "parameters": {
    "subscriptionId": "ryfyipwunzucqdsukyvgjgcaoyuvvu",
    "resourceGroupName": "rgspringbootsites",
    "springbootsitesName": "ibwqwnmvmimwzyxwqkwzkemoetzvaodxkiatbftbkgugpcqqsddeeobfgxwcto",
    "api-version": "2023-01-01-preview"
  },
  "responses": {
    "200": {
      "body": {
        "properties": {
          "provisioningState": "zijghltpkldmhnaoe"
        },
        "id": "kteoiquxsffuhwftoddrxukiqud",
        "name": "kxmhnfajskdaennieej",
        "type": "scygrzvunydtfnybslhra",
        "location": "wjuzknomjxvybhef",
        "tags": {
          "key4111": "tcajshidiltqlcoysteefmz"
        },
        "extendedLocation": {
          "type": "z",
          "name": "dcgidqrefmkwkam"
        }
      }
    }
  }
}