{
  "operationId": "Operations_List",
  "title": "OperationsList",
  "parameters": {
    "api-version": "2023-04-01-preview"
  },
  "responses": {
    "200": {
      "body": {
        "value": [
          {
            "name": "Microsoft.OperatorVoicemail/operatorVoicemails/write",
            "display": {
              "provider": "Microsoft.OperatorVoicemail",
              "resource": "operatorVoicemails",
              "operation": "write",
              "description": "Write operatorVoicemails resource"
            }
          }
        ],
        "nextLink": null
      }
    }
  }
}
