{
  "parameters": {
    "api-version": "2022-08-01-preview",
    "subscriptionId": "ezciceocxewafpl",
    "resourceGroupName": "rgsystemintegritymonitoring",
    "simHubName": "Fv-J99",
    "deviceProfileName": "k1nT--m5-3-",
    "resource": {
      "location": "xiqytayeunqvunmhptfgbtrvy"
    }
  },
  "responses": {
    "200": {
      "body": {
        "location": "xiqytayeunqvunmhptfgbtrvy"
      }
    },
    "201": {
      "headers": {
        "Azure-AsyncOperation": "https://contoso.com/operationstatus"
      },
      "body": {
        "location": "xiqytayeunqvunmhptfgbtrvy"
      }
    }
  }
}