{
  "parameters": {
    "api-version": "2022-04-01-preview",
    "subscriptionId": "subid",
    "resourceGroupName": "rg1",
    "virtualMachineName": "myvm"
  },
  "responses": {
    "200": {
      "body": {
        "name": "myvm",
        "id": "/subscriptions/subid/resourceGroups/rg1/providers/Microsoft.Elephant/virtualMachines/myvm",
        "type": "Microsoft.Elephant/virtualMachines",
        "location": "southcentralus",
        "properties": {
          "provisioningState": "Succeeded",
          "osProfile": {
            "computerName": "acctProcessor",
            "adminUsername": "contosoVMAdmin",
            "adminPassword": "asecret"
          },
          "storageProfile": {
            "imageReference": {
              "id": "/subscriptions/{subscription-id}/resourceGroups/myResourceGroup/providers/Microsoft.Compute/galleries/mySharedGallery/images/mySharedImage"
            }
          },
          "hardwareProfile": {
            "vmSize": "Standard_DS1_v2"
          }
        }
      }
    }
  }
}