{
  "title": "Datasets_ListByInstance",
  "operationId": "Datasets_ListByInstance",
  "parameters": {
    "api-version": "2023-06-26-preview",
    "subscriptionId": "FA56F0AD-0D9F-43D7-8F1C-3FE48CAA3BC5",
    "resourceGroupName": "rgopenapi",
    "instanceName": "D-3A-H--FQYT3Jkl4f-lYe4"
  },
  "responses": {
    "200": {
      "body": {
        "value": [
          {
            "properties": {
              "displayName": "drl",
              "payload": "sbjdjrblwutdrad",
              "timestamp": "glctcmzrdxpyrseenfhoydikplb",
              "ttl": "jsalumuaq",
              "keys": {},
              "provisioningState": "Succeeded"
            },
            "id": "fnnufkwypuocjjkefzprxeqmrpn",
            "name": "ckbdhoaht",
            "type": "pntfebvmiwdkytgwostgvuz",
            "systemData": {
              "createdBy": "msnijxfzjzumunrsrsvagreju",
              "createdByType": "User",
              "createdAt": "2023-07-14T15:53:54.568Z",
              "lastModifiedBy": "lfybp",
              "lastModifiedByType": "User",
              "lastModifiedAt": "2023-07-14T15:53:54.568Z"
            }
          }
        ],
        "nextLink": "https://microsoft.com/a"
      }
    }
  }
}