{
  "parameters": {
    "subscriptionId": "mySubscriptionId",
    "resourceGroupName": "myResourceGroup",
    "resourceName": "serviceTypeEnablement1",
    "api-version": "2021-08-10-privatepreview",
    "location": "West US",
    "properties": {
      "subscriptionId": "mySubscriptionId",
      "ResourceProviderNamespace" : "Microsoft.Cache",
      "ResourceTypeName" : "Redis"
    }
  },
  "responses": {
    "200": {
      "body": {
        "id": "/subscriptions/mySubscriptionId/resourceGroups/myResourceGroup/providers/Microsoft.AzureCIS/serviceTypeEnablements/serviceTypeEnablement1",
        "name": "serviceTypeEnablement1",
        "type": "microsoft.azurecis/serviceTypeEnablements",
        "location": "West US",
        "properties": {
            "subscriptionId": "mySubscriptionId",
            "resourceProviderNamespace": "Microsoft.Cache",
            "resourceTypeName": "Redis",
            "provisioningState": "Succeeded"
        }
      }
    },
    "201": {
      "body": {
        "id": "/subscriptions/mySubscriptionId/resourceGroups/myResourceGroup/providers/Microsoft.AzureCIS/serviceTypeEnablements/serviceTypeEnablement1",
        "name": "serviceTypeEnablement1",
        "type": "microsoft.azurecis/serviceTypeEnablements",
        "location": "West US",
        "properties": {
            "subscriptionId": "mySubscriptionId",
            "resourceProviderNamespace": "Microsoft.Cache",
            "resourceTypeName": "Redis",
            "provisioningState": "Succeeded"
        }
      }
    }
  }
}
